{
  "hash": "2de7397b",
  "configHash": "e4563676",
  "lockfileHash": "cd24f8d2",
  "browserHash": "aa9f2797",
  "optimized": {
    "react": {
      "src": "../../node_modules/react/index.js",
      "file": "react.js",
      "fileHash": "c1e2fe4e",
      "needsInterop": true
    },
    "react-dom": {
      "src": "../../node_modules/react-dom/index.js",
      "file": "react-dom.js",
      "fileHash": "a0df388e",
      "needsInterop": true
    },
    "react/jsx-dev-runtime": {
      "src": "../../node_modules/react/jsx-dev-runtime.js",
      "file": "react_jsx-dev-runtime.js",
      "fileHash": "1b7f56b0",
      "needsInterop": true
    },
    "react/jsx-runtime": {
      "src": "../../node_modules/react/jsx-runtime.js",
      "file": "react_jsx-runtime.js",
      "fileHash": "e622a1f3",
      "needsInterop": true
    }
  },
  "chunks": {
    "chunk-KHA5YKM3": {
      "file": "chunk-KHA5YKM3.js"
    }
  }
}